{"segmented": 0, "object": [{"name": "Signature", "pose": "Unspecified", "truncated": 0, "difficult": 0, "bndbox": {"xmin": 301, "ymin": 1721, "xmax": 451, "ymax": 1850}}, {"name": "Signature", "pose": "Unspecified", "truncated": 0, "difficult": 0, "bndbox": {"xmin": 315, "ymin": 1853, "xmax": 399, "ymax": 1953}}, {"name": "Signature", "pose": "Unspecified", "truncated": 0, "difficult": 0, "bndbox": {"xmin": 738, "ymin": 1811, "xmax": 828, "ymax": 1934}}, {"name": "Signature", "pose": "Unspecified", "truncated": 0, "difficult": 0, "bndbox": {"xmin": 1059, "ymin": 1758, "xmax": 1233, "ymax": 1884}}, {"name": "Signature", "pose": "Unspecified", "truncated": 0, "difficult": 0, "bndbox": {"xmin": 1312, "ymin": 1884, "xmax": 1488, "ymax": 1997}}], "size": {"width": 1665, "height": 2332, "depth": 3}}